curation_projects/__init__.py
curation_projects/importer_main.py
subhaashita/__init__.py
subhaashita/db/__init__.py
subhaashita/db/toml_md_db.py
subhaashita/importer/__init__.py
subhaashita/importer/subhaashita_ratna_bhaandaagaara.py
subhaashita-0.0.1.dist-info/LICENSE.txt
subhaashita-0.0.1.dist-info/METADATA
subhaashita-0.0.1.dist-info/WHEEL
subhaashita-0.0.1.dist-info/top_level.txt
subhaashita-0.0.1.dist-info/RECORD
