Metadata-Version: 2.1
Name: subhaashita
Version: 0.0.1
Summary: A package for curating subhaashita-s (quotes) in various languages.
Home-page: https://github.com/sanskrit-coders/doc_curation
Author: Sanskrit programmers
Author-email: sanskrit-programmers@googlegroups.com
License: MIT
Keywords: quotes subhAShita subhasita
Platform: UNKNOWN
Classifier: Development Status :: 5 - Production/Stable
Classifier: Intended Audience :: Education
Classifier: Topic :: Text Processing :: Linguistic
Classifier: License :: OSI Approved :: MIT License
Classifier: Programming Language :: Python :: 3
Classifier: Programming Language :: Python :: 3.10
Requires-Dist: editdistance
Requires-Dist: methodtools
Requires-Dist: indic-transliteration
Requires-Dist: sanskrit-data
Requires-Dist: curation-utils
Requires-Dist: doc-curation
Provides-Extra: test
Requires-Dist: pytest ; extra == 'test'
